{"Tomsk": {"TOMSK": [{"map_id": "2515029", "fuzzy_ratio": 91, "year": 1842.0, "overlap_confidence": 0.4155557476346554}, {"map_id": "1646010", "fuzzy_ratio": 91, "year": 1915.0, "overlap_confidence": 0.004660744681046427}, {"map_id": "11233055", "fuzzy_ratio": 91, "year": 1829.0, "overlap_confidence": 0.6179675156417964}]}, "geojson": {"type": "Feature", "score": 41.34227, "properties": {"title": "Tomsk", "index_id": "13923967", "index_role": "parent", "place_id": 5378673, "child_place_ids": [90422], "dataset": "tgn_filtered_01", "fclasses": ["P"], "placetypes": ["inhabited place", "city"], "variants": [], "links": [{"identifier": "tgn:7011601", "type": "closeMatch"}], "timespans": [{"gte": 1600, "lte": 1914}, {"gte": 1840, "lte": 1910}, {"gte": 1917, "lte": 1930}, {"gte": -6000, "lte": -2000}, {"gte": 1580, "lte": 1932}, {"gte": 1917, "lte": 1924}, {"gte": 1985, "lte": 2005}], "minmax": [], "ccodes": ["RU"]}, "geometry": {"coordinates": [85.0833, 56.5], "type": "Point"}}}